odoo8_addon_l10n_ar_base_country_state-8.0.1.1.0-py2.7-nspkg.pth
odoo8_addon_l10n_ar_base_country_state-8.0.1.1.0.dist-info/top_level.txt
odoo8_addon_l10n_ar_base_country_state-8.0.1.1.0.dist-info/WHEEL
odoo8_addon_l10n_ar_base_country_state-8.0.1.1.0.dist-info/RECORD
odoo8_addon_l10n_ar_base_country_state-8.0.1.1.0.dist-info/metadata.json
odoo8_addon_l10n_ar_base_country_state-8.0.1.1.0.dist-info/DESCRIPTION.rst
odoo8_addon_l10n_ar_base_country_state-8.0.1.1.0.dist-info/METADATA
odoo8_addon_l10n_ar_base_country_state-8.0.1.1.0.dist-info/namespace_packages.txt
odoo_addons/l10n_ar_base_country_state/README.md
odoo_addons/l10n_ar_base_country_state/__openerp__.py
odoo_addons/l10n_ar_base_country_state/__init__.py
odoo_addons/l10n_ar_base_country_state/AUTHORS
odoo_addons/l10n_ar_base_country_state/models/partner.py
odoo_addons/l10n_ar_base_country_state/models/__init__.py
odoo_addons/l10n_ar_base_country_state/models/res_city.py
odoo_addons/l10n_ar_base_country_state/views/res_city_view.xml
odoo_addons/l10n_ar_base_country_state/views/partner_view.xml
odoo_addons/l10n_ar_base_country_state/data/res_city_data.xml
odoo_addons/l10n_ar_base_country_state/data/country_state_data.xml
odoo_addons/l10n_ar_base_country_state/static/description/icon.png
