Metadata-Version: 2.0
Name: odoo8-addon-l10n-ar-base-country-state
Version: 8.0.1.1.0
Summary: Base Argentina's States (aka Provinces)
Home-page: UNKNOWN
Author: UNKNOWN
Author-email: UNKNOWN
License: UNKNOWN
Platform: UNKNOWN
Requires-Dist: odoo (<9.0a,>=8.0a)
Classifier: Programming Language :: Python :: 2.7
Classifier: Framework :: Odoo
